yubikey_unlock_session.py
yubikey_unlock_session-0.4.0.dist-info/METADATA
yubikey_unlock_session-0.4.0.dist-info/WHEEL
yubikey_unlock_session-0.4.0.dist-info/entry_points.txt
yubikey_unlock_session-0.4.0.dist-info/RECORD
